proyecto_dp/__init__.py
proyecto_dp-0.0.1.dist-info/METADATA
proyecto_dp-0.0.1.dist-info/WHEEL
proyecto_dp-0.0.1.dist-info/top_level.txt
proyecto_dp-0.0.1.dist-info/RECORD
